{
   "OrderTime" : "21:25:31",
   "Customers" : [
      {
         "CustomerLName" : "Anderson",
         "CustomerNote" : "",
         "CustomerEmail" : "anderson@mail.com",
         "CustomerCity" : "Dewsbury",
         "CustomerPostCode" : "Wf134hr",
         "CustomerAddress" : "CENSORED",
         "CustomerPhone" : "70820914798",
         "CustomerCountry" : "UK"
      }
   ],
   "Acknowledged" : false,
   "OrderDate" : "2065-11-18",
   "MyallocatorModificationDate" : "2017-12-10",
   "EndDate" : "2017-12-14",
   "OrderId" : "83ej4zyzp",
   "IsCancellation" : false,
   "Version" : 0,
   "MyallocatorId" : "03e02be5338e030b12bb4f890",
   "ma_callback_qbid" : 8691100,
   "TotalPrice" : "20.00",
   "MyallocatorCreationDate" : "2017-12-10",
   "IsModification" : false,
   "MyallocatorModificationTime" : "10:43:13",
   "PropertyId" : "42429",
   "StartDate" : "2017-12-14",
   "MyallocatorCreationTime" : "10:43:13",
   "MarkedAsRead" : false,
   "Channel" : "lr",
   "TotalCurrency" : "GBP",
   "Rooms" : [
      {
         "EndDate" : "2017-12-14",
         "OccupantFName" : "",
         "RoomTypeIds" : [
            79748
         ],
         "RoomDesc" : "Male Dormitory - Single Bed Single Room sleeps 1. Breakfast included.  Non Smoking Requested, 1 Adult (One Bed in Air conditioned  spacious  room with a contract q)",
         "Price" : "20.00",
         "RoomSummary" : "Male Dormitory - Single Bed Single Room sleeps 1. Breakfast included.  Non Smoking Requested, 1 Adult",
         "Units" : "1",
         "StartDate" : "2017-12-14",
         "MyallocatorRateplanIds" : [],
         "ChannelRoomType" : "4706035"
      }
   ]
}
