{
   "OrderTime" : "11:11:16",
   "DepositDue" : "0.00",
   "Deposit" : "0.00",
   "Customers" : [
      {
         "CustomerLName" : "Harris",
         "CustomerCompany" : "",
         "CustomerNote" : "",
         "CustomerEmail" : "michael.harris@hushmail.com",
         "CustomerFName" : "Michael",
         "CustomerPostCode" : "",
         "CustomerCity" : "",
         "CustomerAddress" : "CENSORED",
         "CustomerPhone" : "23500685583",
         "CustomerCountry" : "kr"
      }
   ],
   "Acknowledged" : false,
   "OrderDate" : "2017-10-31",
   "TotalTaxesCurrency" : "KRW",
   "MyallocatorModificationDate" : "2017-10-31",
   "OrderId" : "4175477162",
   "EndDate" : "2017-11-09",
   "IsCancellation" : false,
   "Version" : 0,
   "MyallocatorId" : "1f7753209a4f2ba7f19b5c9f5",
   "CommissionCurrency" : "KRW",
   "TotalPrice" : "9000.00",
   "MyallocatorCreationDate" : "2017-10-31",
   "IsModification" : false,
   "MyallocatorModificationTime" : "11:11:18",
   "PropertyId" : "3586",
   "StartDate" : "2017-11-09",
   "MyallocatorCreationTime" : "11:11:18",
   "MarkedAsRead" : false,
   "Channel" : "ya",
   "Commission" : 0,
   "TotalCurrency" : "KRW",
   "TotalTaxes" : 0,
   "Rooms" : [
      {
         "DayRates" : [
            {
               "RateId" : "97450",
               "Rate" : 9000,
               "Date" : "2017-11-09",
               "Description" : null
            }
         ],
         "OccupantLName" : "",
         "Units" : "1",
         "Occupancy" : 1,
         "StartDate" : "2017-11-09",
         "EndDate" : "2017-11-09",
         "OccupantFName" : "",
         "RoomTypeIds" : [
            50927
         ],
         "RateId" : "97450",
         "RoomDesc" : "14-bed Mixed Dorm ",
         "RateDesc" : "",
         "Price" : "9000.00",
         "Currency" : "KRW",
         "OccupantNote" : "",
         "Policy" : "",
         "MyallocatorRateplanIds" : [],
         "ChannelRoomType" : "76267"
      }
   ]
}
